dcss_api-0.4.0.dist-info/METADATA
dcss_api-0.4.0.dist-info/WHEEL
dcss_api.libs/libgcc_s-98a1ef30.so.1
dcss_api/__init__.py
dcss_api/dcss_api.cpython-313-x86_64-linux-musl.so
dcss_api-0.4.0.dist-info/RECORD
