Metadata-Version: 2.4
Name: dcss-api
Version: 0.4.0
Summary: A DCSS Webtile API for Python.
Author: Eric Fecteau <eric.m.fecteau@gmail.com>
Author-email: Eric Fecteau <eric.m.fecteau@gmail.com>
License: MPL-2.0
Project-URL: Source Code, https://github.com/EricFecteau/dcss-api/
